rocksmap.py
rocksmap-0.0.1.dist-info/LICENSE.txt
rocksmap-0.0.1.dist-info/METADATA
rocksmap-0.0.1.dist-info/WHEEL
rocksmap-0.0.1.dist-info/top_level.txt
rocksmap-0.0.1.dist-info/RECORD
